UIrecorder/FileReader.py
UIrecorder/FileRecorder.py
UIrecorder/Models.py
UIrecorder/Player.py
UIrecorder/Recorder.py
UIrecorder/TimerClass.py
UIrecorder/__init__.py
UIrecorder-1.1.dist-info/LICENSE.txt
UIrecorder-1.1.dist-info/METADATA
UIrecorder-1.1.dist-info/WHEEL
UIrecorder-1.1.dist-info/entry_points.txt
UIrecorder-1.1.dist-info/top_level.txt
UIrecorder-1.1.dist-info/RECORD
