Metadata-Version: 2.1
Name: UIrecorder
Version: 1.1
Summary: No readme
Home-page: https://github.com/abadiag/UIrecorder
Author: Albert Badia
Author-email: abgsoftdevelop@gmail.com
License: CopyRight 2020
Platform: UNKNOWN
Classifier: Development Status :: 3 - Alpha
Classifier: Intended Audience :: Developers
Classifier: Topic :: Software Development :: Build Tools
Classifier: License :: OSI Approved :: MIT License
Classifier: Programming Language :: Python :: 3.6
Requires-Dist: pynput
Requires-Dist: pyautogui
